pysuncalc/__init__.py
pysuncalc/_version.py
pysuncalc-0.0.1.dist-info/METADATA
pysuncalc-0.0.1.dist-info/WHEEL
pysuncalc-0.0.1.dist-info/licenses/LICENSE
pysuncalc-0.0.1.dist-info/RECORD
