Metadata-Version: 2.1
Name: pysuncalc
Version: 0.0.1
Summary: Library for sun timings calculations. Python port of JS library SunCalc
Project-URL: Homepage, https://github.com/es7s/pysuncalc
Author-email: Aleksandr Shavykin <0.delameter@gmail.com>
License: MIT
License-File: LICENSE
Keywords: astronomy,calculator,sun,sunrise,sunset,zenith
Classifier: Development Status :: 5 - Production/Stable
Classifier: Intended Audience :: Developers
Classifier: License :: OSI Approved :: MIT License
Classifier: Operating System :: OS Independent
Classifier: Programming Language :: Python
Classifier: Programming Language :: Python :: 3
Classifier: Programming Language :: Python :: 3.8
Classifier: Programming Language :: Python :: 3.9
Classifier: Programming Language :: Python :: 3.10
Classifier: Topic :: Software Development :: Libraries
Requires-Python: >=3.8
